image_cytof/__init__.py
image_cytof/hyperion_preprocess.py
image_cytof/hyperion_segmentation.py
image_cytof/segmentation_functions.py
tests/__init__.py
tests/test_preprocess.py
imageCyTOF-0.0.1.dist-info/METADATA
imageCyTOF-0.0.1.dist-info/WHEEL
imageCyTOF-0.0.1.dist-info/top_level.txt
imageCyTOF-0.0.1.dist-info/RECORD
