Metadata-Version: 2.1
Name: imageCyTOF
Version: 0.0.1
Summary: Image Cytof analysis Python Package
Home-page: UNKNOWN
Author: Shidan Wang and Dannie Sheng
Author-email: <hudanyun.sheng@gmail.com>
License: UNKNOWN
Keywords: python,image_cytof
Platform: UNKNOWN
Classifier: Development Status :: 3 - Alpha
Classifier: Intended Audience :: Education
Classifier: Programming Language :: Python :: 3
Classifier: Operating System :: MacOS :: MacOS X
Classifier: Operating System :: Microsoft :: Windows
